{
  "$schema": "http://cyclonedx.org/schema/bom-1.6.schema.json",
  "version": 1,
  "metadata": {
    "tools": [
      {
        "name": "trivy",
        "vendor": "aquasecurity",
        "version": "unknown"
      }
    ],
    "component": {
      "name": "tomcat",
      "purl": "pkg:oci/tomcat@9.0.70-jdk8-corretto?digest=sha256:93d42e4f4a441739bea9361d59917263d65d4d9b3c0e946b4ccd3ce939812f9c",
      "type": "library",
      "bom-ref": "pkg:oci/tomcat@9.0.70-jdk8-corretto?digest=sha256:93d42e4f4a441739bea9361d59917263d65d4d9b3c0e946b4ccd3ce939812f9c",
      "version": "9.0.70-jdk8-corretto"
    },
    "timestamp": "2024-10-19T19:37:02.052857+00:00"
  },
  "bomFormat": "CycloneDX",
  "components": [
    {
      "name": "2c55629b-cc91-45dc-988b-2cf9689eaa1d",
      "type": "library",
      "bom-ref": "BomRef.7958113284835122.8956586277046765",
      "version": "unknown"
    },
    {
      "name": "amazon",
      "type": "library",
      "bom-ref": "BomRef.22219313044209776.18808922021972918",
      "version": "2 (Karoo)"
    },
    {
      "name": "amazon-linux-extras",
      "type": "library",
      "bom-ref": "BomRef.17167385280203662.5311187481123368",
      "version": "2.0.1-1.amzn2"
    },
    {
      "name": "apr",
      "type": "library",
      "bom-ref": "BomRef.025295149269627504.8414669465129304",
      "version": "1.7.0-9.amzn2"
    },
    {
      "name": "basesystem",
      "type": "library",
      "bom-ref": "BomRef.858155205960467.21581761615022133",
      "version": "10.0-7.amzn2.0.1"
    },
    {
      "name": "bash",
      "type": "library",
      "bom-ref": "BomRef.44511421971960474.2372168641203516",
      "version": "4.2.46-34.amzn2"
    },
    {
      "name": "bzip2-libs",
      "type": "library",
      "bom-ref": "BomRef.47149787444060154.8902691181260931",
      "version": "1.0.6-13.amzn2.0.3"
    },
    {
      "name": "ca-certificates",
      "type": "library",
      "bom-ref": "BomRef.251537048304346.5005325666393251",
      "version": "2021.2.50-72.amzn2.0.3"
    },
    {
      "name": "chkconfig",
      "type": "library",
      "bom-ref": "BomRef.5852695049603781.9134287684946485",
      "version": "1.7.4-1.amzn2.0.2"
    },
    {
      "name": "commons-daemon",
      "type": "library",
      "bom-ref": "BomRef.4332150928287344.7065713403098943",
      "version": "1.3.3"
    },
    {
      "name": "coreutils",
      "type": "library",
      "bom-ref": "BomRef.8539035724795038.41542171097367386",
      "version": "8.22-24.amzn2"
    },
    {
      "name": "cpio",
      "type": "library",
      "bom-ref": "BomRef.8976575313785282.2914042026667628",
      "version": "2.11-28.amzn2"
    },
    {
      "name": "curl",
      "type": "library",
      "bom-ref": "BomRef.6905230875766468.24682986596963696",
      "version": "7.79.1-7.amzn2.0.1"
    },
    {
      "name": "cyrus-sasl-lib",
      "type": "library",
      "bom-ref": "BomRef.16173929747576932.8872161670530829",
      "version": "2.1.26-24.amzn2"
    },
    {
      "name": "dejavu-fonts-common",
      "type": "library",
      "bom-ref": "BomRef.03339074331216885.3188713807186522",
      "version": "2.33-6.amzn2"
    },
    {
      "name": "dejavu-sans-fonts",
      "type": "library",
      "bom-ref": "BomRef.3207145307095982.6978047928762252",
      "version": "2.33-6.amzn2"
    },
    {
      "name": "diffutils",
      "type": "library",
      "bom-ref": "BomRef.7024103039190571.6097066509142984",
      "version": "3.3-5.amzn2"
    },
    {
      "name": "elfutils-libelf",
      "type": "library",
      "bom-ref": "BomRef.5251403681174225.07841039477913292",
      "version": "0.176-2.amzn2"
    },
    {
      "name": "expat",
      "type": "library",
      "bom-ref": "BomRef.0035630277068516847.34788069831357815",
      "version": "2.1.0-15.amzn2.0.2"
    },
    {
      "name": "file-libs",
      "type": "library",
      "bom-ref": "BomRef.5334431523884916.7990645009699633",
      "version": "5.11-36.amzn2.0.1"
    },
    {
      "name": "filesystem",
      "type": "library",
      "bom-ref": "BomRef.5432439236730557.1073254811412715",
      "version": "3.2-25.amzn2.0.4"
    },
    {
      "name": "findutils",
      "type": "library",
      "bom-ref": "BomRef.6029353764700056.588245875339538",
      "version": "1:4.5.11-6.amzn2"
    },
    {
      "name": "fontconfig",
      "type": "library",
      "bom-ref": "BomRef.23141321568324302.23173845792832248",
      "version": "2.13.0-4.3.amzn2"
    },
    {
      "name": "fontpackages-filesystem",
      "type": "library",
      "bom-ref": "BomRef.35335305338327405.3759625309452961",
      "version": "1.44-8.amzn2"
    },
    {
      "name": "freetype",
      "type": "library",
      "bom-ref": "BomRef.8161794048283197.3362457299824254",
      "version": "2.8-14.amzn2.1"
    },
    {
      "name": "gawk",
      "type": "library",
      "bom-ref": "BomRef.2184711287908827.1419380358948541",
      "version": "4.0.2-4.amzn2.1.2"
    },
    {
      "name": "gdbm",
      "type": "library",
      "bom-ref": "BomRef.3481024200346844.9869917203056577",
      "version": "1:1.13-6.amzn2.0.2"
    },
    {
      "name": "glib2",
      "type": "library",
      "bom-ref": "BomRef.25684005608963445.051982655765296704",
      "version": "2.56.1-9.amzn2.0.2"
    },
    {
      "name": "glibc",
      "type": "library",
      "bom-ref": "BomRef.6346216305408744.6144272239685917",
      "version": "2.26-62.amzn2"
    },
    {
      "name": "glibc-common",
      "type": "library",
      "bom-ref": "BomRef.737936946998565.18598325302298013",
      "version": "2.26-62.amzn2"
    },
    {
      "name": "glibc-langpack-en",
      "type": "library",
      "bom-ref": "BomRef.31010031991354936.8893650556821875",
      "version": "2.26-62.amzn2"
    },
    {
      "name": "glibc-minimal-langpack",
      "type": "library",
      "bom-ref": "BomRef.9414083722861952.7553647359376754",
      "version": "2.26-62.amzn2"
    },
    {
      "name": "gmp",
      "type": "library",
      "bom-ref": "BomRef.3296973027258866.5097190006324973",
      "version": "1:6.0.0-15.amzn2.0.2"
    },
    {
      "name": "gnupg2",
      "type": "library",
      "bom-ref": "BomRef.20835658578268057.7545467164833245",
      "version": "2.0.22-5.amzn2.0.5"
    },
    {
      "name": "gpg-pubkey",
      "type": "library",
      "bom-ref": "BomRef.7899100850130666.40491384981354894",
      "version": "b04f24e3-5de94a19"
    },
    {
      "name": "gpg-pubkey",
      "type": "library",
      "bom-ref": "BomRef.4057132859789465.9201080560125651",
      "version": "c87f5b1a-593863f8"
    },
    {
      "name": "gpgme",
      "type": "library",
      "bom-ref": "BomRef.25846218655874553.023540006096414712",
      "version": "1.3.2-5.amzn2.0.2"
    },
    {
      "name": "grep",
      "type": "library",
      "bom-ref": "BomRef.22322305500655615.7259018798645404",
      "version": "2.20-3.amzn2.0.2"
    },
    {
      "name": "info",
      "type": "library",
      "bom-ref": "BomRef.9565753312499307.9762125310998879",
      "version": "5.1-5.amzn2"
    },
    {
      "name": "java-1.8.0-amazon-corretto-devel",
      "type": "library",
      "bom-ref": "BomRef.039609365541825925.4650890568347327",
      "version": "1:1.8.0_352.b08-1"
    },
    {
      "name": "keyutils-libs",
      "type": "library",
      "bom-ref": "BomRef.11808006121211145.9136288674349349",
      "version": "1.5.8-3.amzn2.0.2"
    },
    {
      "name": "krb5-libs",
      "type": "library",
      "bom-ref": "BomRef.2873633954717466.5535403179959095",
      "version": "1.15.1-37.amzn2.2.4"
    },
    {
      "name": "libacl",
      "type": "library",
      "bom-ref": "BomRef.4596064525678152.346646905019781",
      "version": "2.2.51-14.amzn2"
    },
    {
      "name": "libassuan",
      "type": "library",
      "bom-ref": "BomRef.7908515018216623.21528889751206648",
      "version": "2.1.0-3.amzn2.0.2"
    },
    {
      "name": "libattr",
      "type": "library",
      "bom-ref": "BomRef.07268367392223707.3982109485165506",
      "version": "2.4.46-12.amzn2.0.2"
    },
    {
      "name": "libblkid",
      "type": "library",
      "bom-ref": "BomRef.3477145517965913.8899302806195817",
      "version": "2.30.2-2.amzn2.0.10"
    },
    {
      "name": "libcap",
      "type": "library",
      "bom-ref": "BomRef.3925809375842787.8008994554688549",
      "version": "2.54-1.amzn2.0.1"
    },
    {
      "name": "libcom_err",
      "type": "library",
      "bom-ref": "BomRef.09530598133011892.26477424285906914",
      "version": "1.42.9-19.amzn2.0.1"
    },
    {
      "name": "libcrypt",
      "type": "library",
      "bom-ref": "BomRef.6813533464145896.7599568182049437",
      "version": "2.26-62.amzn2"
    },
    {
      "name": "libcurl",
      "type": "library",
      "bom-ref": "BomRef.9497066492793391.30328190280453016",
      "version": "7.79.1-7.amzn2.0.1"
    },
    {
      "name": "libdb",
      "type": "library",
      "bom-ref": "BomRef.8218577507745715.8953983124629376",
      "version": "5.3.21-24.amzn2.0.3"
    },
    {
      "name": "libdb-utils",
      "type": "library",
      "bom-ref": "BomRef.4753725220583813.3827155181118329",
      "version": "5.3.21-24.amzn2.0.3"
    },
    {
      "name": "libffi",
      "type": "library",
      "bom-ref": "BomRef.1345852956217738.8939240068957326",
      "version": "3.0.13-18.amzn2.0.2"
    },
    {
      "name": "libgcc",
      "type": "library",
      "bom-ref": "BomRef.4229789637855441.1460474663629001",
      "version": "7.3.1-15.amzn2"
    },
    {
      "name": "libgcrypt",
      "type": "library",
      "bom-ref": "BomRef.8999332631300351.5822771674740229",
      "version": "1.5.3-14.amzn2.0.3"
    },
    {
      "name": "libgpg-error",
      "type": "library",
      "bom-ref": "BomRef.6176153901015593.26000802744580176",
      "version": "1.12-3.amzn2.0.3"
    },
    {
      "name": "libidn2",
      "type": "library",
      "bom-ref": "BomRef.7370740613860806.21362891363552272",
      "version": "2.3.0-1.amzn2"
    },
    {
      "name": "libmetalink",
      "type": "library",
      "bom-ref": "BomRef.7975154259919881.36301840856229795",
      "version": "0.1.3-13.amzn2"
    },
    {
      "name": "libmount",
      "type": "library",
      "bom-ref": "BomRef.7653190340656153.6991233921976238",
      "version": "2.30.2-2.amzn2.0.10"
    },
    {
      "name": "libnghttp2",
      "type": "library",
      "bom-ref": "BomRef.3773776805572848.23351173862201702",
      "version": "1.41.0-1.amzn2"
    },
    {
      "name": "libpng",
      "type": "library",
      "bom-ref": "BomRef.1306250432733057.9833875354353265",
      "version": "2:1.5.13-8.amzn2"
    },
    {
      "name": "libselinux",
      "type": "library",
      "bom-ref": "BomRef.900909762249451.2471445380985453",
      "version": "2.5-12.amzn2.0.2"
    },
    {
      "name": "libsepol",
      "type": "library",
      "bom-ref": "BomRef.22543845512421035.07580705229318907",
      "version": "2.5-8.1.amzn2.0.2"
    },
    {
      "name": "libssh2",
      "type": "library",
      "bom-ref": "BomRef.4780380484421286.4501137849361958",
      "version": "1.4.3-12.amzn2.2.3"
    },
    {
      "name": "libstdc++",
      "type": "library",
      "bom-ref": "BomRef.09543390922248007.37725492866851484",
      "version": "7.3.1-15.amzn2"
    },
    {
      "name": "libtasn1",
      "type": "library",
      "bom-ref": "BomRef.18174864459036222.8392115375244704",
      "version": "4.10-1.amzn2.0.2"
    },
    {
      "name": "libunistring",
      "type": "library",
      "bom-ref": "BomRef.104184760759366.9641630516882661",
      "version": "0.9.3-9.amzn2.0.2"
    },
    {
      "name": "libuuid",
      "type": "library",
      "bom-ref": "BomRef.1928098138627412.22162106785403124",
      "version": "2.30.2-2.amzn2.0.10"
    },
    {
      "name": "libverto",
      "type": "library",
      "bom-ref": "BomRef.3873623856203078.988632204137638",
      "version": "0.2.5-4.amzn2.0.2"
    },
    {
      "name": "libxml2",
      "type": "library",
      "bom-ref": "BomRef.013815427444148431.9711292275871117",
      "version": "2.9.1-6.amzn2.5.6"
    },
    {
      "name": "lua",
      "type": "library",
      "bom-ref": "BomRef.11075272586353913.5411272225418162",
      "version": "5.1.4-15.amzn2.0.2"
    },
    {
      "name": "ncurses",
      "type": "library",
      "bom-ref": "BomRef.12687764016661762.27258319889775984",
      "version": "6.0-8.20170212.amzn2.1.4"
    },
    {
      "name": "ncurses-base",
      "type": "library",
      "bom-ref": "BomRef.0018159720216502917.7278583532015503",
      "version": "6.0-8.20170212.amzn2.1.4"
    },
    {
      "name": "ncurses-libs",
      "type": "library",
      "bom-ref": "BomRef.40425564798806934.35936938820893904",
      "version": "6.0-8.20170212.amzn2.1.4"
    },
    {
      "name": "nspr",
      "type": "library",
      "bom-ref": "BomRef.23580104330413765.611528235415045",
      "version": "4.34.0-3.1.amzn2"
    },
    {
      "name": "nss",
      "type": "library",
      "bom-ref": "BomRef.3459249345148202.7826137119515066",
      "version": "3.79.0-4.amzn2"
    },
    {
      "name": "nss-pem",
      "type": "library",
      "bom-ref": "BomRef.5385626187911724.6197900783544131",
      "version": "1.0.3-5.amzn2"
    },
    {
      "name": "nss-softokn",
      "type": "library",
      "bom-ref": "BomRef.6647904219132164.9431811920417164",
      "version": "3.79.0-4.amzn2"
    },
    {
      "name": "nss-softokn-freebl",
      "type": "library",
      "bom-ref": "BomRef.4464815583687167.5676416688092596",
      "version": "3.79.0-4.amzn2"
    },
    {
      "name": "nss-sysinit",
      "type": "library",
      "bom-ref": "BomRef.5834045117863439.6701370175415429",
      "version": "3.79.0-4.amzn2"
    },
    {
      "name": "nss-tools",
      "type": "library",
      "bom-ref": "BomRef.09613787870217028.028285942197263325",
      "version": "3.79.0-4.amzn2"
    },
    {
      "name": "nss-util",
      "type": "library",
      "bom-ref": "BomRef.9136498816516799.4942325872386133",
      "version": "3.79.0-1.amzn2"
    },
    {
      "name": "openldap",
      "type": "library",
      "bom-ref": "BomRef.48510772204240515.01610398379080613",
      "version": "2.4.44-23.amzn2.0.4"
    },
    {
      "name": "openssl-libs",
      "type": "library",
      "bom-ref": "BomRef.45000904472512826.11234631717478016",
      "version": "1:1.0.2k-24.amzn2.0.4"
    },
    {
      "name": "openssl11-libs",
      "type": "library",
      "bom-ref": "BomRef.02979587136401929.1070087129761298",
      "version": "1:1.1.1g-12.amzn2.0.9"
    },
    {
      "name": "openssl11-pkcs11",
      "type": "library",
      "bom-ref": "BomRef.17485222034003423.3263128649505064",
      "version": "0.4.10-6.amzn2.0.1"
    },
    {
      "name": "p11-kit",
      "type": "library",
      "bom-ref": "BomRef.44766284115186505.5433824599208427",
      "version": "0.23.22-1.amzn2.0.1"
    },
    {
      "name": "p11-kit-trust",
      "type": "library",
      "bom-ref": "BomRef.9626647589522044.7048965793322094",
      "version": "0.23.22-1.amzn2.0.1"
    },
    {
      "name": "pcre",
      "type": "library",
      "bom-ref": "BomRef.9765370120590116.10861593621240972",
      "version": "8.32-17.amzn2.0.2"
    },
    {
      "name": "pinentry",
      "type": "library",
      "bom-ref": "BomRef.15304201089770242.36036912060642323",
      "version": "0.8.1-17.amzn2.0.2"
    },
    {
      "name": "pkg:maven/commons-daemon/commons-daemon@1.3.3",
      "type": "library",
      "bom-ref": "BomRef.5990787889226832.3917259225513092",
      "version": "unknown"
    },
    {
      "name": "pkg:maven/org.apache.taglibs/taglibs-standard-impl@1.2.5",
      "type": "library",
      "bom-ref": "BomRef.8323112021785808.19369969194680703",
      "version": "unknown"
    },
    {
      "name": "pkg:maven/org.apache.taglibs/taglibs-standard-spec@1.2.5",
      "type": "library",
      "bom-ref": "BomRef.6772436204217235.5812130418147848",
      "version": "unknown"
    },
    {
      "name": "pkg:maven/org.apache.tomcat/tomcat-annotations-api@9.0.70",
      "type": "library",
      "bom-ref": "BomRef.14639827735184152.8100529945700642",
      "version": "unknown"
    },
    {
      "name": "pkg:maven/org.apache.tomcat/tomcat-api@9.0.70",
      "type": "library",
      "bom-ref": "BomRef.3327266175021557.5372064892065355",
      "version": "unknown"
    },
    {
      "name": "pkg:maven/org.apache.tomcat/tomcat-catalina-ant@9.0.70",
      "type": "library",
      "bom-ref": "BomRef.9119207184919825.2852014807529095",
      "version": "unknown"
    },
    {
      "name": "pkg:maven/org.apache.tomcat/tomcat-catalina-ha@9.0.70",
      "type": "library",
      "bom-ref": "BomRef.23373836527391423.728442297836659",
      "version": "unknown"
    },
    {
      "name": "pkg:maven/org.apache.tomcat/tomcat-catalina@9.0.70",
      "type": "library",
      "bom-ref": "BomRef.9168960829352993.9985037916173709",
      "version": "unknown"
    },
    {
      "name": "pkg:maven/org.apache.tomcat/tomcat-coyote@9.0.70",
      "type": "library",
      "bom-ref": "BomRef.3971915537463303.551799956122311",
      "version": "unknown"
    },
    {
      "name": "pkg:maven/org.apache.tomcat/tomcat-dbcp@9.0.70",
      "type": "library",
      "bom-ref": "BomRef.7952778068009224.04545893801380796",
      "version": "unknown"
    },
    {
      "name": "pkg:maven/org.apache.tomcat/tomcat-el-api@9.0.70",
      "type": "library",
      "bom-ref": "BomRef.7639158257292504.21522534253298442",
      "version": "unknown"
    },
    {
      "name": "pkg:maven/org.apache.tomcat/tomcat-i18n-cs@9.0.70",
      "type": "library",
      "bom-ref": "BomRef.3243847038058433.6434280073928325",
      "version": "unknown"
    },
    {
      "name": "pkg:maven/org.apache.tomcat/tomcat-i18n-de@9.0.70",
      "type": "library",
      "bom-ref": "BomRef.6863074463388752.04903501527493381",
      "version": "unknown"
    },
    {
      "name": "pkg:maven/org.apache.tomcat/tomcat-i18n-es@9.0.70",
      "type": "library",
      "bom-ref": "BomRef.10870588622353639.5792501550856259",
      "version": "unknown"
    },
    {
      "name": "pkg:maven/org.apache.tomcat/tomcat-i18n-fr@9.0.70",
      "type": "library",
      "bom-ref": "BomRef.3904649021228791.6391495186657729",
      "version": "unknown"
    },
    {
      "name": "pkg:maven/org.apache.tomcat/tomcat-i18n-ja@9.0.70",
      "type": "library",
      "bom-ref": "BomRef.4878951036338821.14080929949471943",
      "version": "unknown"
    },
    {
      "name": "pkg:maven/org.apache.tomcat/tomcat-i18n-ko@9.0.70",
      "type": "library",
      "bom-ref": "BomRef.8649550122428052.08255056361006696",
      "version": "unknown"
    },
    {
      "name": "pkg:maven/org.apache.tomcat/tomcat-i18n-pt-BR@9.0.70",
      "type": "library",
      "bom-ref": "BomRef.4163039673839164.8721598338563111",
      "version": "unknown"
    },
    {
      "name": "pkg:maven/org.apache.tomcat/tomcat-i18n-ru@9.0.70",
      "type": "library",
      "bom-ref": "BomRef.5143856245989535.31479272286686777",
      "version": "unknown"
    },
    {
      "name": "pkg:maven/org.apache.tomcat/tomcat-i18n-zh-CN@9.0.70",
      "type": "library",
      "bom-ref": "BomRef.6151382959114065.603255116026117",
      "version": "unknown"
    },
    {
      "name": "pkg:maven/org.apache.tomcat/tomcat-jasper-el@9.0.70",
      "type": "library",
      "bom-ref": "BomRef.1536463230913827.08985439939334261",
      "version": "unknown"
    },
    {
      "name": "pkg:maven/org.apache.tomcat/tomcat-jasper@9.0.70",
      "type": "library",
      "bom-ref": "BomRef.6462312813033937.2621479055848642",
      "version": "unknown"
    },
    {
      "name": "pkg:maven/org.apache.tomcat/tomcat-jaspic-api@9.0.70",
      "type": "library",
      "bom-ref": "BomRef.24935674284071674.555881687061498",
      "version": "unknown"
    },
    {
      "name": "pkg:maven/org.apache.tomcat/tomcat-jdbc@9.0.70",
      "type": "library",
      "bom-ref": "BomRef.13342310505568067.8544589307764973",
      "version": "unknown"
    },
    {
      "name": "pkg:maven/org.apache.tomcat/tomcat-jni@9.0.70",
      "type": "library",
      "bom-ref": "BomRef.4332046246233626.795259628287604",
      "version": "unknown"
    },
    {
      "name": "pkg:maven/org.apache.tomcat/tomcat-jsp-api@9.0.70",
      "type": "library",
      "bom-ref": "BomRef.7404108814614824.8235380783396934",
      "version": "unknown"
    },
    {
      "name": "pkg:maven/org.apache.tomcat/tomcat-juli@9.0.70",
      "type": "library",
      "bom-ref": "BomRef.9681147578453106.6688275495043436",
      "version": "unknown"
    },
    {
      "name": "pkg:maven/org.apache.tomcat/tomcat-servlet-api@9.0.70",
      "type": "library",
      "bom-ref": "BomRef.5161906080021347.42942914405884414",
      "version": "unknown"
    },
    {
      "name": "pkg:maven/org.apache.tomcat/tomcat-ssi@9.0.70",
      "type": "library",
      "bom-ref": "BomRef.34127043868134643.866309060882704",
      "version": "unknown"
    },
    {
      "name": "pkg:maven/org.apache.tomcat/tomcat-storeconfig@9.0.70",
      "type": "library",
      "bom-ref": "BomRef.1386048560966291.26928365330098536",
      "version": "unknown"
    },
    {
      "name": "pkg:maven/org.apache.tomcat/tomcat-tribes@9.0.70",
      "type": "library",
      "bom-ref": "BomRef.6626674822066282.5753537363610373",
      "version": "unknown"
    },
    {
      "name": "pkg:maven/org.apache.tomcat/tomcat-util-scan@9.0.70",
      "type": "library",
      "bom-ref": "BomRef.1221444837164426.8227553219357557",
      "version": "unknown"
    },
    {
      "name": "pkg:maven/org.apache.tomcat/tomcat-util@9.0.70",
      "type": "library",
      "bom-ref": "BomRef.1465022172445608.9873832541034251",
      "version": "unknown"
    },
    {
      "name": "pkg:maven/org.apache.tomcat/tomcat-websocket-api@9.0.70",
      "type": "library",
      "bom-ref": "BomRef.07075682868164312.7759608145017209",
      "version": "unknown"
    },
    {
      "name": "pkg:maven/org.apache.tomcat/tomcat-websocket@9.0.70",
      "type": "library",
      "bom-ref": "BomRef.23127033617182946.5323053389621224",
      "version": "unknown"
    },
    {
      "name": "pkg:oci/tomcat@sha256%3A93d42e4f4a441739bea9361d59917263d65d4d9b3c0e946b4ccd3ce939812f9c?arch=amd64&repository_url=index.docker.io%2Flibrary%2Ftomcat",
      "type": "library",
      "bom-ref": "BomRef.25732223634157314.5912645938585508",
      "version": "unknown"
    },
    {
      "name": "pkg:rpm/amazon/amazon-linux-extras@2.0.1-1.amzn2?arch=noarch&distro=amazon-2+%28Karoo%29",
      "type": "library",
      "bom-ref": "BomRef.10322392442929362.7727491022392801",
      "version": "unknown"
    },
    {
      "name": "pkg:rpm/amazon/apr@1.7.0-9.amzn2?arch=x86_64&distro=amazon-2+%28Karoo%29",
      "type": "library",
      "bom-ref": "BomRef.5182111008141962.38052236075242407",
      "version": "unknown"
    },
    {
      "name": "pkg:rpm/amazon/basesystem@10.0-7.amzn2.0.1?arch=noarch&distro=amazon-2+%28Karoo%29",
      "type": "library",
      "bom-ref": "BomRef.35008985117432023.19585014351176389",
      "version": "unknown"
    },
    {
      "name": "pkg:rpm/amazon/bash@4.2.46-34.amzn2?arch=x86_64&distro=amazon-2+%28Karoo%29",
      "type": "library",
      "bom-ref": "BomRef.1770443783939466.5140651192506216",
      "version": "unknown"
    },
    {
      "name": "pkg:rpm/amazon/bzip2-libs@1.0.6-13.amzn2.0.3?arch=x86_64&distro=amazon-2+%28Karoo%29",
      "type": "library",
      "bom-ref": "BomRef.26622475399874324.2879557273623502",
      "version": "unknown"
    },
    {
      "name": "pkg:rpm/amazon/ca-certificates@2021.2.50-72.amzn2.0.3?arch=noarch&distro=amazon-2+%28Karoo%29",
      "type": "library",
      "bom-ref": "BomRef.682710492317654.42864415874214024",
      "version": "unknown"
    },
    {
      "name": "pkg:rpm/amazon/chkconfig@1.7.4-1.amzn2.0.2?arch=x86_64&distro=amazon-2+%28Karoo%29",
      "type": "library",
      "bom-ref": "BomRef.08970936003800445.48019475208765916",
      "version": "unknown"
    },
    {
      "name": "pkg:rpm/amazon/coreutils@8.22-24.amzn2?arch=x86_64&distro=amazon-2+%28Karoo%29",
      "type": "library",
      "bom-ref": "BomRef.3138472453565493.8555064766797252",
      "version": "unknown"
    },
    {
      "name": "pkg:rpm/amazon/cpio@2.11-28.amzn2?arch=x86_64&distro=amazon-2+%28Karoo%29",
      "type": "library",
      "bom-ref": "BomRef.5601384922185327.8133206776698153",
      "version": "unknown"
    },
    {
      "name": "pkg:rpm/amazon/curl@7.79.1-7.amzn2.0.1?arch=x86_64&distro=amazon-2+%28Karoo%29",
      "type": "library",
      "bom-ref": "BomRef.3391512983596001.45219231548076877",
      "version": "unknown"
    },
    {
      "name": "pkg:rpm/amazon/cyrus-sasl-lib@2.1.26-24.amzn2?arch=x86_64&distro=amazon-2+%28Karoo%29",
      "type": "library",
      "bom-ref": "BomRef.5003552210738995.3907062292777187",
      "version": "unknown"
    },
    {
      "name": "pkg:rpm/amazon/dejavu-fonts-common@2.33-6.amzn2?arch=noarch&distro=amazon-2+%28Karoo%29",
      "type": "library",
      "bom-ref": "BomRef.600442768005774.6500937067157797",
      "version": "unknown"
    },
    {
      "name": "pkg:rpm/amazon/dejavu-sans-fonts@2.33-6.amzn2?arch=noarch&distro=amazon-2+%28Karoo%29",
      "type": "library",
      "bom-ref": "BomRef.98036271256211.5157746391137943",
      "version": "unknown"
    },
    {
      "name": "pkg:rpm/amazon/diffutils@3.3-5.amzn2?arch=x86_64&distro=amazon-2+%28Karoo%29",
      "type": "library",
      "bom-ref": "BomRef.6901366936913301.9919808150445804",
      "version": "unknown"
    },
    {
      "name": "pkg:rpm/amazon/elfutils-libelf@0.176-2.amzn2?arch=x86_64&distro=amazon-2+%28Karoo%29",
      "type": "library",
      "bom-ref": "BomRef.3408896473274503.9368487815019755",
      "version": "unknown"
    },
    {
      "name": "pkg:rpm/amazon/expat@2.1.0-15.amzn2.0.2?arch=x86_64&distro=amazon-2+%28Karoo%29",
      "type": "library",
      "bom-ref": "BomRef.963240332319471.9749109075176594",
      "version": "unknown"
    },
    {
      "name": "pkg:rpm/amazon/file-libs@5.11-36.amzn2.0.1?arch=x86_64&distro=amazon-2+%28Karoo%29",
      "type": "library",
      "bom-ref": "BomRef.5262991904152454.9679632655820538",
      "version": "unknown"
    },
    {
      "name": "pkg:rpm/amazon/filesystem@3.2-25.amzn2.0.4?arch=x86_64&distro=amazon-2+%28Karoo%29",
      "type": "library",
      "bom-ref": "BomRef.36377914192901684.7255922589274026",
      "version": "unknown"
    },
    {
      "name": "pkg:rpm/amazon/findutils@4.5.11-6.amzn2?arch=x86_64&distro=amazon-2+%28Karoo%29&epoch=1",
      "type": "library",
      "bom-ref": "BomRef.852237618535223.38176432624242973",
      "version": "unknown"
    },
    {
      "name": "pkg:rpm/amazon/fontconfig@2.13.0-4.3.amzn2?arch=x86_64&distro=amazon-2+%28Karoo%29",
      "type": "library",
      "bom-ref": "BomRef.3361937290990057.5415170028242486",
      "version": "unknown"
    },
    {
      "name": "pkg:rpm/amazon/fontpackages-filesystem@1.44-8.amzn2?arch=noarch&distro=amazon-2+%28Karoo%29",
      "type": "library",
      "bom-ref": "BomRef.9835140225109988.3152794327734316",
      "version": "unknown"
    },
    {
      "name": "pkg:rpm/amazon/freetype@2.8-14.amzn2.1?arch=x86_64&distro=amazon-2+%28Karoo%29",
      "type": "library",
      "bom-ref": "BomRef.43053608972442137.6032402051851337",
      "version": "unknown"
    },
    {
      "name": "pkg:rpm/amazon/gawk@4.0.2-4.amzn2.1.2?arch=x86_64&distro=amazon-2+%28Karoo%29",
      "type": "library",
      "bom-ref": "BomRef.06020692649238013.06418343785152214",
      "version": "unknown"
    },
    {
      "name": "pkg:rpm/amazon/gdbm@1.13-6.amzn2.0.2?arch=x86_64&distro=amazon-2+%28Karoo%29&epoch=1",
      "type": "library",
      "bom-ref": "BomRef.7369724763288075.46114252730429817",
      "version": "unknown"
    },
    {
      "name": "pkg:rpm/amazon/glib2@2.56.1-9.amzn2.0.2?arch=x86_64&distro=amazon-2+%28Karoo%29",
      "type": "library",
      "bom-ref": "BomRef.7512641397111998.7551288420976054",
      "version": "unknown"
    },
    {
      "name": "pkg:rpm/amazon/glibc-common@2.26-62.amzn2?arch=x86_64&distro=amazon-2+%28Karoo%29",
      "type": "library",
      "bom-ref": "BomRef.4932871677499093.0224189405438473",
      "version": "unknown"
    },
    {
      "name": "pkg:rpm/amazon/glibc-langpack-en@2.26-62.amzn2?arch=x86_64&distro=amazon-2+%28Karoo%29",
      "type": "library",
      "bom-ref": "BomRef.39170836227087913.7703282097772005",
      "version": "unknown"
    },
    {
      "name": "pkg:rpm/amazon/glibc-minimal-langpack@2.26-62.amzn2?arch=x86_64&distro=amazon-2+%28Karoo%29",
      "type": "library",
      "bom-ref": "BomRef.8215994508676511.00854632602919303",
      "version": "unknown"
    },
    {
      "name": "pkg:rpm/amazon/glibc@2.26-62.amzn2?arch=x86_64&distro=amazon-2+%28Karoo%29",
      "type": "library",
      "bom-ref": "BomRef.9203214545372581.05810994057543206",
      "version": "unknown"
    },
    {
      "name": "pkg:rpm/amazon/gmp@6.0.0-15.amzn2.0.2?arch=x86_64&distro=amazon-2+%28Karoo%29&epoch=1",
      "type": "library",
      "bom-ref": "BomRef.7121768012460298.6831042096395753",
      "version": "unknown"
    },
    {
      "name": "pkg:rpm/amazon/gnupg2@2.0.22-5.amzn2.0.5?arch=x86_64&distro=amazon-2+%28Karoo%29",
      "type": "library",
      "bom-ref": "BomRef.1627680874005738.5186609440312644",
      "version": "unknown"
    },
    {
      "name": "pkg:rpm/amazon/gpg-pubkey@b04f24e3-5de94a19?arch=None&distro=amazon-2+%28Karoo%29",
      "type": "library",
      "bom-ref": "BomRef.16541512516813095.9052564952770752",
      "version": "unknown"
    },
    {
      "name": "pkg:rpm/amazon/gpg-pubkey@c87f5b1a-593863f8?arch=None&distro=amazon-2+%28Karoo%29",
      "type": "library",
      "bom-ref": "BomRef.9338470409129607.2521853204965865",
      "version": "unknown"
    },
    {
      "name": "pkg:rpm/amazon/gpgme@1.3.2-5.amzn2.0.2?arch=x86_64&distro=amazon-2+%28Karoo%29",
      "type": "library",
      "bom-ref": "BomRef.6127446047378282.9359435920398181",
      "version": "unknown"
    },
    {
      "name": "pkg:rpm/amazon/grep@2.20-3.amzn2.0.2?arch=x86_64&distro=amazon-2+%28Karoo%29",
      "type": "library",
      "bom-ref": "BomRef.13341543270359424.01229782532099899",
      "version": "unknown"
    },
    {
      "name": "pkg:rpm/amazon/info@5.1-5.amzn2?arch=x86_64&distro=amazon-2+%28Karoo%29",
      "type": "library",
      "bom-ref": "BomRef.011778688048470931.22352707167100394",
      "version": "unknown"
    },
    {
      "name": "pkg:rpm/amazon/java-1.8.0-amazon-corretto-devel@1.8.0_352.b08-1?arch=x86_64&distro=amazon-2+%28Karoo%29&epoch=1",
      "type": "library",
      "bom-ref": "BomRef.4328767306113661.40246422189266073",
      "version": "unknown"
    },
    {
      "name": "pkg:rpm/amazon/keyutils-libs@1.5.8-3.amzn2.0.2?arch=x86_64&distro=amazon-2+%28Karoo%29",
      "type": "library",
      "bom-ref": "BomRef.5424360438525592.030663887187034278",
      "version": "unknown"
    },
    {
      "name": "pkg:rpm/amazon/krb5-libs@1.15.1-37.amzn2.2.4?arch=x86_64&distro=amazon-2+%28Karoo%29",
      "type": "library",
      "bom-ref": "BomRef.14905616759135554.050103478276885216",
      "version": "unknown"
    },
    {
      "name": "pkg:rpm/amazon/libacl@2.2.51-14.amzn2?arch=x86_64&distro=amazon-2+%28Karoo%29",
      "type": "library",
      "bom-ref": "BomRef.1327657337657685.3242234189013058",
      "version": "unknown"
    },
    {
      "name": "pkg:rpm/amazon/libassuan@2.1.0-3.amzn2.0.2?arch=x86_64&distro=amazon-2+%28Karoo%29",
      "type": "library",
      "bom-ref": "BomRef.12615683546768774.27374617166213633",
      "version": "unknown"
    },
    {
      "name": "pkg:rpm/amazon/libattr@2.4.46-12.amzn2.0.2?arch=x86_64&distro=amazon-2+%28Karoo%29",
      "type": "library",
      "bom-ref": "BomRef.014237553556579963.7480174564174986",
      "version": "unknown"
    },
    {
      "name": "pkg:rpm/amazon/libblkid@2.30.2-2.amzn2.0.10?arch=x86_64&distro=amazon-2+%28Karoo%29",
      "type": "library",
      "bom-ref": "BomRef.4057145430137862.2571275299377813",
      "version": "unknown"
    },
    {
      "name": "pkg:rpm/amazon/libcap@2.54-1.amzn2.0.1?arch=x86_64&distro=amazon-2+%28Karoo%29",
      "type": "library",
      "bom-ref": "BomRef.3656307793308552.24327716599539562",
      "version": "unknown"
    },
    {
      "name": "pkg:rpm/amazon/libcom_err@1.42.9-19.amzn2.0.1?arch=x86_64&distro=amazon-2+%28Karoo%29",
      "type": "library",
      "bom-ref": "BomRef.8052639961416493.6147689178085999",
      "version": "unknown"
    },
    {
      "name": "pkg:rpm/amazon/libcrypt@2.26-62.amzn2?arch=x86_64&distro=amazon-2+%28Karoo%29",
      "type": "library",
      "bom-ref": "BomRef.8932264348629707.9145182314928945",
      "version": "unknown"
    },
    {
      "name": "pkg:rpm/amazon/libcurl@7.79.1-7.amzn2.0.1?arch=x86_64&distro=amazon-2+%28Karoo%29",
      "type": "library",
      "bom-ref": "BomRef.6544864846486909.04028590421938172",
      "version": "unknown"
    },
    {
      "name": "pkg:rpm/amazon/libdb-utils@5.3.21-24.amzn2.0.3?arch=x86_64&distro=amazon-2+%28Karoo%29",
      "type": "library",
      "bom-ref": "BomRef.35828333124285006.6001766890266548",
      "version": "unknown"
    },
    {
      "name": "pkg:rpm/amazon/libdb@5.3.21-24.amzn2.0.3?arch=x86_64&distro=amazon-2+%28Karoo%29",
      "type": "library",
      "bom-ref": "BomRef.34826734434729323.6776748954012676",
      "version": "unknown"
    },
    {
      "name": "pkg:rpm/amazon/libffi@3.0.13-18.amzn2.0.2?arch=x86_64&distro=amazon-2+%28Karoo%29",
      "type": "library",
      "bom-ref": "BomRef.9323151371034749.7106707591562522",
      "version": "unknown"
    },
    {
      "name": "pkg:rpm/amazon/libgcc@7.3.1-15.amzn2?arch=x86_64&distro=amazon-2+%28Karoo%29",
      "type": "library",
      "bom-ref": "BomRef.24717121630101402.07694692293647698",
      "version": "unknown"
    },
    {
      "name": "pkg:rpm/amazon/libgcrypt@1.5.3-14.amzn2.0.3?arch=x86_64&distro=amazon-2+%28Karoo%29",
      "type": "library",
      "bom-ref": "BomRef.9826696735306814.46239869143739676",
      "version": "unknown"
    },
    {
      "name": "pkg:rpm/amazon/libgpg-error@1.12-3.amzn2.0.3?arch=x86_64&distro=amazon-2+%28Karoo%29",
      "type": "library",
      "bom-ref": "BomRef.4113561898744106.7392348054747258",
      "version": "unknown"
    },
    {
      "name": "pkg:rpm/amazon/libidn2@2.3.0-1.amzn2?arch=x86_64&distro=amazon-2+%28Karoo%29",
      "type": "library",
      "bom-ref": "BomRef.1534385245076082.9825835538864264",
      "version": "unknown"
    },
    {
      "name": "pkg:rpm/amazon/libmetalink@0.1.3-13.amzn2?arch=x86_64&distro=amazon-2+%28Karoo%29",
      "type": "library",
      "bom-ref": "BomRef.1251784585184137.15926619193105784",
      "version": "unknown"
    },
    {
      "name": "pkg:rpm/amazon/libmount@2.30.2-2.amzn2.0.10?arch=x86_64&distro=amazon-2+%28Karoo%29",
      "type": "library",
      "bom-ref": "BomRef.8981077033738266.39562307316455336",
      "version": "unknown"
    },
    {
      "name": "pkg:rpm/amazon/libnghttp2@1.41.0-1.amzn2?arch=x86_64&distro=amazon-2+%28Karoo%29",
      "type": "library",
      "bom-ref": "BomRef.8499271343700612.8696909254878976",
      "version": "unknown"
    },
    {
      "name": "pkg:rpm/amazon/libpng@1.5.13-8.amzn2?arch=x86_64&distro=amazon-2+%28Karoo%29&epoch=2",
      "type": "library",
      "bom-ref": "BomRef.7976660706590307.030706747349566466",
      "version": "unknown"
    },
    {
      "name": "pkg:rpm/amazon/libselinux@2.5-12.amzn2.0.2?arch=x86_64&distro=amazon-2+%28Karoo%29",
      "type": "library",
      "bom-ref": "BomRef.7496955586628976.9258868812329143",
      "version": "unknown"
    },
    {
      "name": "pkg:rpm/amazon/libsepol@2.5-8.1.amzn2.0.2?arch=x86_64&distro=amazon-2+%28Karoo%29",
      "type": "library",
      "bom-ref": "BomRef.19797194730623924.5016579949849717",
      "version": "unknown"
    },
    {
      "name": "pkg:rpm/amazon/libssh2@1.4.3-12.amzn2.2.3?arch=x86_64&distro=amazon-2+%28Karoo%29",
      "type": "library",
      "bom-ref": "BomRef.6120550821978259.25270254343500387",
      "version": "unknown"
    },
    {
      "name": "pkg:rpm/amazon/libstdc%2B%2B@7.3.1-15.amzn2?arch=x86_64&distro=amazon-2+%28Karoo%29",
      "type": "library",
      "bom-ref": "BomRef.7217190445856247.6026094728385979",
      "version": "unknown"
    },
    {
      "name": "pkg:rpm/amazon/libtasn1@4.10-1.amzn2.0.2?arch=x86_64&distro=amazon-2+%28Karoo%29",
      "type": "library",
      "bom-ref": "BomRef.1327220946308606.2861368968213518",
      "version": "unknown"
    },
    {
      "name": "pkg:rpm/amazon/libunistring@0.9.3-9.amzn2.0.2?arch=x86_64&distro=amazon-2+%28Karoo%29",
      "type": "library",
      "bom-ref": "BomRef.6605638518627277.01090445794710082",
      "version": "unknown"
    },
    {
      "name": "pkg:rpm/amazon/libuuid@2.30.2-2.amzn2.0.10?arch=x86_64&distro=amazon-2+%28Karoo%29",
      "type": "library",
      "bom-ref": "BomRef.9229369251969962.3566474889180804",
      "version": "unknown"
    },
    {
      "name": "pkg:rpm/amazon/libverto@0.2.5-4.amzn2.0.2?arch=x86_64&distro=amazon-2+%28Karoo%29",
      "type": "library",
      "bom-ref": "BomRef.33873635126331325.04658383771796082",
      "version": "unknown"
    },
    {
      "name": "pkg:rpm/amazon/libxml2@2.9.1-6.amzn2.5.6?arch=x86_64&distro=amazon-2+%28Karoo%29",
      "type": "library",
      "bom-ref": "BomRef.7060923243670211.14971721147863426",
      "version": "unknown"
    },
    {
      "name": "pkg:rpm/amazon/lua@5.1.4-15.amzn2.0.2?arch=x86_64&distro=amazon-2+%28Karoo%29",
      "type": "library",
      "bom-ref": "BomRef.28629903892246567.07367799981057188",
      "version": "unknown"
    },
    {
      "name": "pkg:rpm/amazon/ncurses-base@6.0-8.20170212.amzn2.1.4?arch=noarch&distro=amazon-2+%28Karoo%29",
      "type": "library",
      "bom-ref": "BomRef.27036339601431003.7051994140302649",
      "version": "unknown"
    },
    {
      "name": "pkg:rpm/amazon/ncurses-libs@6.0-8.20170212.amzn2.1.4?arch=x86_64&distro=amazon-2+%28Karoo%29",
      "type": "library",
      "bom-ref": "BomRef.740487180202749.7161350696325692",
      "version": "unknown"
    },
    {
      "name": "pkg:rpm/amazon/ncurses@6.0-8.20170212.amzn2.1.4?arch=x86_64&distro=amazon-2+%28Karoo%29",
      "type": "library",
      "bom-ref": "BomRef.5705031417022018.14384537981158685",
      "version": "unknown"
    },
    {
      "name": "pkg:rpm/amazon/nspr@4.34.0-3.1.amzn2?arch=x86_64&distro=amazon-2+%28Karoo%29",
      "type": "library",
      "bom-ref": "BomRef.4343177735279167.0818065469150101",
      "version": "unknown"
    },
    {
      "name": "pkg:rpm/amazon/nss-pem@1.0.3-5.amzn2?arch=x86_64&distro=amazon-2+%28Karoo%29",
      "type": "library",
      "bom-ref": "BomRef.6765455978351402.8395952836629234",
      "version": "unknown"
    },
    {
      "name": "pkg:rpm/amazon/nss-softokn-freebl@3.79.0-4.amzn2?arch=x86_64&distro=amazon-2+%28Karoo%29",
      "type": "library",
      "bom-ref": "BomRef.12653998161655167.6696903719481841",
      "version": "unknown"
    },
    {
      "name": "pkg:rpm/amazon/nss-softokn@3.79.0-4.amzn2?arch=x86_64&distro=amazon-2+%28Karoo%29",
      "type": "library",
      "bom-ref": "BomRef.2718892667322874.009678597920913967",
      "version": "unknown"
    },
    {
      "name": "pkg:rpm/amazon/nss-sysinit@3.79.0-4.amzn2?arch=x86_64&distro=amazon-2+%28Karoo%29",
      "type": "library",
      "bom-ref": "BomRef.23094932474050278.5740898052130355",
      "version": "unknown"
    },
    {
      "name": "pkg:rpm/amazon/nss-tools@3.79.0-4.amzn2?arch=x86_64&distro=amazon-2+%28Karoo%29",
      "type": "library",
      "bom-ref": "BomRef.24297854408542374.19366761939615362",
      "version": "unknown"
    },
    {
      "name": "pkg:rpm/amazon/nss-util@3.79.0-1.amzn2?arch=x86_64&distro=amazon-2+%28Karoo%29",
      "type": "library",
      "bom-ref": "BomRef.04657273264806916.677565532276889",
      "version": "unknown"
    },
    {
      "name": "pkg:rpm/amazon/nss@3.79.0-4.amzn2?arch=x86_64&distro=amazon-2+%28Karoo%29",
      "type": "library",
      "bom-ref": "BomRef.1433240813212171.6392183393420439",
      "version": "unknown"
    },
    {
      "name": "pkg:rpm/amazon/openldap@2.4.44-23.amzn2.0.4?arch=x86_64&distro=amazon-2+%28Karoo%29",
      "type": "library",
      "bom-ref": "BomRef.7108283339811768.9438567408422134",
      "version": "unknown"
    },
    {
      "name": "pkg:rpm/amazon/openssl-libs@1.0.2k-24.amzn2.0.4?arch=x86_64&distro=amazon-2+%28Karoo%29&epoch=1",
      "type": "library",
      "bom-ref": "BomRef.8470423003993348.01881575672729252",
      "version": "unknown"
    },
    {
      "name": "pkg:rpm/amazon/openssl11-libs@1.1.1g-12.amzn2.0.9?arch=x86_64&distro=amazon-2+%28Karoo%29&epoch=1",
      "type": "library",
      "bom-ref": "BomRef.16851407482773595.7080761122825618",
      "version": "unknown"
    },
    {
      "name": "pkg:rpm/amazon/openssl11-pkcs11@0.4.10-6.amzn2.0.1?arch=x86_64&distro=amazon-2+%28Karoo%29",
      "type": "library",
      "bom-ref": "BomRef.5339868961406974.43470824808629094",
      "version": "unknown"
    },
    {
      "name": "pkg:rpm/amazon/p11-kit-trust@0.23.22-1.amzn2.0.1?arch=x86_64&distro=amazon-2+%28Karoo%29",
      "type": "library",
      "bom-ref": "BomRef.7656164204429826.21401876124320707",
      "version": "unknown"
    },
    {
      "name": "pkg:rpm/amazon/p11-kit@0.23.22-1.amzn2.0.1?arch=x86_64&distro=amazon-2+%28Karoo%29",
      "type": "library",
      "bom-ref": "BomRef.20152316681322413.11971995223583687",
      "version": "unknown"
    },
    {
      "name": "pkg:rpm/amazon/pcre@8.32-17.amzn2.0.2?arch=x86_64&distro=amazon-2+%28Karoo%29",
      "type": "library",
      "bom-ref": "BomRef.5653994102778257.17328362019203847",
      "version": "unknown"
    },
    {
      "name": "pkg:rpm/amazon/pinentry@0.8.1-17.amzn2.0.2?arch=x86_64&distro=amazon-2+%28Karoo%29",
      "type": "library",
      "bom-ref": "BomRef.2718569389293576.31509873141412714",
      "version": "unknown"
    },
    {
      "name": "pkg:rpm/amazon/popt@1.13-16.amzn2.0.2?arch=x86_64&distro=amazon-2+%28Karoo%29",
      "type": "library",
      "bom-ref": "BomRef.32322304689592296.4371370821480344",
      "version": "unknown"
    },
    {
      "name": "pkg:rpm/amazon/pth@2.0.7-23.amzn2.0.2?arch=x86_64&distro=amazon-2+%28Karoo%29",
      "type": "library",
      "bom-ref": "BomRef.041474408515578154.29461221901426937",
      "version": "unknown"
    },
    {
      "name": "pkg:rpm/amazon/pygpgme@0.3-9.amzn2.0.3?arch=x86_64&distro=amazon-2+%28Karoo%29",
      "type": "library",
      "bom-ref": "BomRef.9826538464816856.4249924816879952",
      "version": "unknown"
    },
    {
      "name": "pkg:rpm/amazon/pyliblzma@0.5.3-25.amzn2?arch=x86_64&distro=amazon-2+%28Karoo%29",
      "type": "library",
      "bom-ref": "BomRef.20197738668356569.12362760966499176",
      "version": "unknown"
    },
    {
      "name": "pkg:rpm/amazon/python-iniparse@0.4-9.amzn2?arch=noarch&distro=amazon-2+%28Karoo%29",
      "type": "library",
      "bom-ref": "BomRef.1849337867826515.006010181925209412",
      "version": "unknown"
    },
    {
      "name": "pkg:rpm/amazon/python-libs@2.7.18-1.amzn2.0.5?arch=x86_64&distro=amazon-2+%28Karoo%29",
      "type": "library",
      "bom-ref": "BomRef.846494587719508.4409436280768897",
      "version": "unknown"
    },
    {
      "name": "pkg:rpm/amazon/python-pycurl@7.19.0-19.amzn2.0.2?arch=x86_64&distro=amazon-2+%28Karoo%29",
      "type": "library",
      "bom-ref": "BomRef.5516933293426147.38897780280154215",
      "version": "unknown"
    },
    {
      "name": "pkg:rpm/amazon/python-urlgrabber@3.10-9.amzn2.0.1?arch=noarch&distro=amazon-2+%28Karoo%29",
      "type": "library",
      "bom-ref": "BomRef.8987280021314258.09277677697065778",
      "version": "unknown"
    },
    {
      "name": "pkg:rpm/amazon/python2-rpm@4.11.3-48.amzn2.0.2?arch=x86_64&distro=amazon-2+%28Karoo%29",
      "type": "library",
      "bom-ref": "BomRef.5583134261799152.005789343868171426",
      "version": "unknown"
    },
    {
      "name": "pkg:rpm/amazon/python@2.7.18-1.amzn2.0.5?arch=x86_64&distro=amazon-2+%28Karoo%29",
      "type": "library",
      "bom-ref": "BomRef.5720773909119735.655829179847459",
      "version": "unknown"
    },
    {
      "name": "pkg:rpm/amazon/pyxattr@0.5.1-5.amzn2.0.2?arch=x86_64&distro=amazon-2+%28Karoo%29",
      "type": "library",
      "bom-ref": "BomRef.5857884642730372.2447656007169322",
      "version": "unknown"
    },
    {
      "name": "pkg:rpm/amazon/readline@6.2-10.amzn2.0.2?arch=x86_64&distro=amazon-2+%28Karoo%29",
      "type": "library",
      "bom-ref": "BomRef.44216418902636623.06171839754069686",
      "version": "unknown"
    },
    {
      "name": "pkg:rpm/amazon/rpm-build-libs@4.11.3-48.amzn2.0.2?arch=x86_64&distro=amazon-2+%28Karoo%29",
      "type": "library",
      "bom-ref": "BomRef.276387535283111.5133178308141938",
      "version": "unknown"
    },
    {
      "name": "pkg:rpm/amazon/rpm-libs@4.11.3-48.amzn2.0.2?arch=x86_64&distro=amazon-2+%28Karoo%29",
      "type": "library",
      "bom-ref": "BomRef.2836253736820884.9212049784442881",
      "version": "unknown"
    },
    {
      "name": "pkg:rpm/amazon/rpm@4.11.3-48.amzn2.0.2?arch=x86_64&distro=amazon-2+%28Karoo%29",
      "type": "library",
      "bom-ref": "BomRef.20374067573944732.18922272075370095",
      "version": "unknown"
    },
    {
      "name": "pkg:rpm/amazon/sed@4.2.2-5.amzn2.0.2?arch=x86_64&distro=amazon-2+%28Karoo%29",
      "type": "library",
      "bom-ref": "BomRef.39571201244158605.882806601930204",
      "version": "unknown"
    },
    {
      "name": "pkg:rpm/amazon/setup@2.8.71-10.amzn2.0.1?arch=noarch&distro=amazon-2+%28Karoo%29",
      "type": "library",
      "bom-ref": "BomRef.33593225769714563.662417880734105",
      "version": "unknown"
    },
    {
      "name": "pkg:rpm/amazon/shared-mime-info@1.8-4.amzn2?arch=x86_64&distro=amazon-2+%28Karoo%29",
      "type": "library",
      "bom-ref": "BomRef.02920202793639226.4061500698107986",
      "version": "unknown"
    },
    {
      "name": "pkg:rpm/amazon/sqlite@3.7.17-8.amzn2.1.1?arch=x86_64&distro=amazon-2+%28Karoo%29",
      "type": "library",
      "bom-ref": "BomRef.4111481239815634.008889975959184393",
      "version": "unknown"
    },
    {
      "name": "pkg:rpm/amazon/system-release@2-14.amzn2?arch=x86_64&distro=amazon-2+%28Karoo%29&epoch=1",
      "type": "library",
      "bom-ref": "BomRef.06689032713488607.4758234521990906",
      "version": "unknown"
    },
    {
      "name": "pkg:rpm/amazon/tzdata@2022f-1.amzn2.0.1?arch=noarch&distro=amazon-2+%28Karoo%29",
      "type": "library",
      "bom-ref": "BomRef.9502825961959741.014272907473487861",
      "version": "unknown"
    },
    {
      "name": "pkg:rpm/amazon/vim-data@9.0.828-1.amzn2.0.1?arch=noarch&distro=amazon-2+%28Karoo%29&epoch=2",
      "type": "library",
      "bom-ref": "BomRef.21011629014372335.4089891184483605",
      "version": "unknown"
    },
    {
      "name": "pkg:rpm/amazon/vim-minimal@9.0.828-1.amzn2.0.1?arch=x86_64&distro=amazon-2+%28Karoo%29&epoch=2",
      "type": "library",
      "bom-ref": "BomRef.913881848939455.7432187220956539",
      "version": "unknown"
    },
    {
      "name": "pkg:rpm/amazon/xz-libs@5.2.2-1.amzn2.0.3?arch=x86_64&distro=amazon-2+%28Karoo%29",
      "type": "library",
      "bom-ref": "BomRef.6843253347331526.09920479879743993",
      "version": "unknown"
    },
    {
      "name": "pkg:rpm/amazon/yum-metadata-parser@1.1.4-10.amzn2.0.2?arch=x86_64&distro=amazon-2+%28Karoo%29",
      "type": "library",
      "bom-ref": "BomRef.023600669464129753.12663440323180186",
      "version": "unknown"
    },
    {
      "name": "pkg:rpm/amazon/yum-plugin-ovl@1.1.31-46.amzn2.0.1?arch=noarch&distro=amazon-2+%28Karoo%29",
      "type": "library",
      "bom-ref": "BomRef.10222450190787624.8393892854067819",
      "version": "unknown"
    },
    {
      "name": "pkg:rpm/amazon/yum-plugin-priorities@1.1.31-46.amzn2.0.1?arch=noarch&distro=amazon-2+%28Karoo%29",
      "type": "library",
      "bom-ref": "BomRef.9124854810325875.9992646704209204",
      "version": "unknown"
    },
    {
      "name": "pkg:rpm/amazon/yum@3.4.3-158.amzn2.0.6?arch=noarch&distro=amazon-2+%28Karoo%29",
      "type": "library",
      "bom-ref": "BomRef.6170930576622515.48956887652803716",
      "version": "unknown"
    },
    {
      "name": "pkg:rpm/amazon/zlib@1.2.7-19.amzn2.0.2?arch=x86_64&distro=amazon-2+%28Karoo%29",
      "type": "library",
      "bom-ref": "BomRef.6911098846894638.31143684791512527",
      "version": "unknown"
    },
    {
      "name": "popt",
      "type": "library",
      "bom-ref": "BomRef.25791499920134964.39677555165238476",
      "version": "1.13-16.amzn2.0.2"
    },
    {
      "name": "pth",
      "type": "library",
      "bom-ref": "BomRef.7912872795152134.48040140019081556",
      "version": "2.0.7-23.amzn2.0.2"
    },
    {
      "name": "pygpgme",
      "type": "library",
      "bom-ref": "BomRef.9431395505965606.7215658594590812",
      "version": "0.3-9.amzn2.0.3"
    },
    {
      "name": "pyliblzma",
      "type": "library",
      "bom-ref": "BomRef.16792030304685956.554699020554485",
      "version": "0.5.3-25.amzn2"
    },
    {
      "name": "python",
      "type": "library",
      "bom-ref": "BomRef.5916494689057641.7447443405295717",
      "version": "2.7.18-1.amzn2.0.5"
    },
    {
      "name": "python-iniparse",
      "type": "library",
      "bom-ref": "BomRef.14817197870407994.5075396378238253",
      "version": "0.4-9.amzn2"
    },
    {
      "name": "python-libs",
      "type": "library",
      "bom-ref": "BomRef.8862275764384353.9316362234120903",
      "version": "2.7.18-1.amzn2.0.5"
    },
    {
      "name": "python-pycurl",
      "type": "library",
      "bom-ref": "BomRef.4903335268428829.005686469324557741",
      "version": "7.19.0-19.amzn2.0.2"
    },
    {
      "name": "python-urlgrabber",
      "type": "library",
      "bom-ref": "BomRef.8073897311222961.32583908020053953",
      "version": "3.10-9.amzn2.0.1"
    },
    {
      "name": "python2-rpm",
      "type": "library",
      "bom-ref": "BomRef.8625073871317434.9251194753306632",
      "version": "4.11.3-48.amzn2.0.2"
    },
    {
      "name": "pyxattr",
      "type": "library",
      "bom-ref": "BomRef.7306780567283283.910009484611246",
      "version": "0.5.1-5.amzn2.0.2"
    },
    {
      "name": "readline",
      "type": "library",
      "bom-ref": "BomRef.006912398675142262.6368006183016659",
      "version": "6.2-10.amzn2.0.2"
    },
    {
      "name": "rpm",
      "type": "library",
      "bom-ref": "BomRef.4533280492974202.824416915091",
      "version": "4.11.3-48.amzn2.0.2"
    },
    {
      "name": "rpm-build-libs",
      "type": "library",
      "bom-ref": "BomRef.4341661832905582.16991957960361714",
      "version": "4.11.3-48.amzn2.0.2"
    },
    {
      "name": "rpm-libs",
      "type": "library",
      "bom-ref": "BomRef.7456804602700163.26626888603001986",
      "version": "4.11.3-48.amzn2.0.2"
    },
    {
      "name": "sed",
      "type": "library",
      "bom-ref": "BomRef.7332335535825006.9635273963684483",
      "version": "4.2.2-5.amzn2.0.2"
    },
    {
      "name": "setup",
      "type": "library",
      "bom-ref": "BomRef.8341756848387535.13477933004979548",
      "version": "2.8.71-10.amzn2.0.1"
    },
    {
      "name": "shared-mime-info",
      "type": "library",
      "bom-ref": "BomRef.8238929013812966.030589068594395363",
      "version": "1.8-4.amzn2"
    },
    {
      "name": "sqlite",
      "type": "library",
      "bom-ref": "BomRef.5584092863906518.45555823535751716",
      "version": "3.7.17-8.amzn2.1.1"
    },
    {
      "name": "system-release",
      "type": "library",
      "bom-ref": "BomRef.16793730416219266.2801808716669726",
      "version": "1:2-14.amzn2"
    },
    {
      "name": "taglibs-standard-impl",
      "type": "library",
      "bom-ref": "BomRef.057313276622598774.9776153662302206",
      "version": "1.2.5"
    },
    {
      "name": "taglibs-standard-spec",
      "type": "library",
      "bom-ref": "BomRef.7432538448193754.22737816154470392",
      "version": "1.2.5"
    },
    {
      "name": "tomcat-annotations-api",
      "type": "library",
      "bom-ref": "BomRef.9172951059655089.18235788502309047",
      "version": "9.0.70"
    },
    {
      "name": "tomcat-api",
      "type": "library",
      "bom-ref": "BomRef.9293946820657696.028474406284301645",
      "version": "9.0.70"
    },
    {
      "name": "tomcat-catalina",
      "type": "library",
      "bom-ref": "BomRef.8878718790485854.4329488554368076",
      "version": "9.0.70"
    },
    {
      "name": "tomcat-catalina-ant",
      "type": "library",
      "bom-ref": "BomRef.06259665202502329.3451017927482022",
      "version": "9.0.70"
    },
    {
      "name": "tomcat-catalina-ha",
      "type": "library",
      "bom-ref": "BomRef.8076593480616812.025504375254326028",
      "version": "9.0.70"
    },
    {
      "name": "tomcat-coyote",
      "type": "library",
      "bom-ref": "BomRef.46763223007709875.39533186752785854",
      "version": "9.0.70"
    },
    {
      "name": "tomcat-dbcp",
      "type": "library",
      "bom-ref": "BomRef.9392930118593713.03377714464804471",
      "version": "9.0.70"
    },
    {
      "name": "tomcat-el-api",
      "type": "library",
      "bom-ref": "BomRef.7083726510006625.7408208402061585",
      "version": "9.0.70"
    },
    {
      "name": "tomcat-i18n-cs",
      "type": "library",
      "bom-ref": "BomRef.5619578338351288.07469094128218068",
      "version": "9.0.70"
    },
    {
      "name": "tomcat-i18n-de",
      "type": "library",
      "bom-ref": "BomRef.9675185747023164.16839193040169587",
      "version": "9.0.70"
    },
    {
      "name": "tomcat-i18n-es",
      "type": "library",
      "bom-ref": "BomRef.8903178854084978.8122913040999395",
      "version": "9.0.70"
    },
    {
      "name": "tomcat-i18n-fr",
      "type": "library",
      "bom-ref": "BomRef.8584033439899356.8087748123904388",
      "version": "9.0.70"
    },
    {
      "name": "tomcat-i18n-ja",
      "type": "library",
      "bom-ref": "BomRef.3379224207803291.15941274452484044",
      "version": "9.0.70"
    },
    {
      "name": "tomcat-i18n-ko",
      "type": "library",
      "bom-ref": "BomRef.8273649672068532.22268476662144843",
      "version": "9.0.70"
    },
    {
      "name": "tomcat-i18n-pt-BR",
      "type": "library",
      "bom-ref": "BomRef.770330096082.14196121435599818",
      "version": "9.0.70"
    },
    {
      "name": "tomcat-i18n-ru",
      "type": "library",
      "bom-ref": "BomRef.2602288839805458.33356986267987576",
      "version": "9.0.70"
    },
    {
      "name": "tomcat-i18n-zh-CN",
      "type": "library",
      "bom-ref": "BomRef.4078619752080975.44863080079965756",
      "version": "9.0.70"
    },
    {
      "name": "tomcat-jasper",
      "type": "library",
      "bom-ref": "BomRef.08475292186363903.6018528409900756",
      "version": "9.0.70"
    },
    {
      "name": "tomcat-jasper-el",
      "type": "library",
      "bom-ref": "BomRef.7566639174475305.22562845280221755",
      "version": "9.0.70"
    },
    {
      "name": "tomcat-jaspic-api",
      "type": "library",
      "bom-ref": "BomRef.37861571185710496.2828002707878283",
      "version": "9.0.70"
    },
    {
      "name": "tomcat-jdbc",
      "type": "library",
      "bom-ref": "BomRef.45524013444249667.7216126593765714",
      "version": "9.0.70"
    },
    {
      "name": "tomcat-jni",
      "type": "library",
      "bom-ref": "BomRef.32714504131001143.2992682437445213",
      "version": "9.0.70"
    },
    {
      "name": "tomcat-jsp-api",
      "type": "library",
      "bom-ref": "BomRef.46986298307002683.7418385068126757",
      "version": "9.0.70"
    },
    {
      "name": "tomcat-juli",
      "type": "library",
      "bom-ref": "BomRef.8556480701790246.3191276740764548",
      "version": "9.0.70"
    },
    {
      "name": "tomcat-servlet-api",
      "type": "library",
      "bom-ref": "BomRef.8770835651682857.8446927283409736",
      "version": "9.0.70"
    },
    {
      "name": "tomcat-ssi",
      "type": "library",
      "bom-ref": "BomRef.4862980005505837.9071629537158274",
      "version": "9.0.70"
    },
    {
      "name": "tomcat-storeconfig",
      "type": "library",
      "bom-ref": "BomRef.6686601367683058.39502771817966664",
      "version": "9.0.70"
    },
    {
      "name": "tomcat-tribes",
      "type": "library",
      "bom-ref": "BomRef.6284838634327398.3003337996424428",
      "version": "9.0.70"
    },
    {
      "name": "tomcat-util",
      "type": "library",
      "bom-ref": "BomRef.7322872065675041.9842000577204513",
      "version": "9.0.70"
    },
    {
      "name": "tomcat-util-scan",
      "type": "library",
      "bom-ref": "BomRef.004215663645203538.30930630725570707",
      "version": "9.0.70"
    },
    {
      "name": "tomcat-websocket",
      "type": "library",
      "bom-ref": "BomRef.6007384753361936.39896805651472056",
      "version": "9.0.70"
    },
    {
      "name": "tomcat-websocket-api",
      "type": "library",
      "bom-ref": "BomRef.30936223483257197.3256611094106132",
      "version": "9.0.70"
    },
    {
      "name": "tzdata",
      "type": "library",
      "bom-ref": "BomRef.670175967420862.6132685907118344",
      "version": "2022f-1.amzn2.0.1"
    },
    {
      "name": "vim-data",
      "type": "library",
      "bom-ref": "BomRef.8842375263146283.7306104662909028",
      "version": "2:9.0.828-1.amzn2.0.1"
    },
    {
      "name": "vim-minimal",
      "type": "library",
      "bom-ref": "BomRef.7594428262248059.11074467512512376",
      "version": "2:9.0.828-1.amzn2.0.1"
    },
    {
      "name": "xz-libs",
      "type": "library",
      "bom-ref": "BomRef.9746750087204098.4251624987262007",
      "version": "5.2.2-1.amzn2.0.3"
    },
    {
      "name": "yum",
      "type": "library",
      "bom-ref": "BomRef.8575760421906526.7889713879361278",
      "version": "3.4.3-158.amzn2.0.6"
    },
    {
      "name": "yum-metadata-parser",
      "type": "library",
      "bom-ref": "BomRef.7828524875599515.6108137700826161",
      "version": "1.1.4-10.amzn2.0.2"
    },
    {
      "name": "yum-plugin-ovl",
      "type": "library",
      "bom-ref": "BomRef.026725048478927205.9381030242226183",
      "version": "1.1.31-46.amzn2.0.1"
    },
    {
      "name": "yum-plugin-priorities",
      "type": "library",
      "bom-ref": "BomRef.36678025112905366.44799180451080767",
      "version": "1.1.31-46.amzn2.0.1"
    },
    {
      "name": "zlib",
      "type": "library",
      "bom-ref": "BomRef.9066164707350783.2581649911592804",
      "version": "1.2.7-19.amzn2.0.2"
    }
  ],
  "specVersion": "1.6",
  "dependencies": [
    {
      "ref": "BomRef.7958113284835122.8956586277046765"
    },
    {
      "ref": "BomRef.5990787889226832.3917259225513092"
    },
    {
      "ref": "BomRef.8323112021785808.19369969194680703"
    },
    {
      "ref": "BomRef.6772436204217235.5812130418147848"
    },
    {
      "ref": "BomRef.14639827735184152.8100529945700642"
    },
    {
      "ref": "BomRef.3327266175021557.5372064892065355"
    },
    {
      "ref": "BomRef.9119207184919825.2852014807529095"
    },
    {
      "ref": "BomRef.23373836527391423.728442297836659"
    },
    {
      "ref": "BomRef.9168960829352993.9985037916173709"
    },
    {
      "ref": "BomRef.3971915537463303.551799956122311"
    },
    {
      "ref": "BomRef.7952778068009224.04545893801380796"
    },
    {
      "ref": "BomRef.7639158257292504.21522534253298442"
    },
    {
      "ref": "BomRef.3243847038058433.6434280073928325"
    },
    {
      "ref": "BomRef.6863074463388752.04903501527493381"
    },
    {
      "ref": "BomRef.10870588622353639.5792501550856259"
    },
    {
      "ref": "BomRef.3904649021228791.6391495186657729"
    },
    {
      "ref": "BomRef.4878951036338821.14080929949471943"
    },
    {
      "ref": "BomRef.8649550122428052.08255056361006696"
    },
    {
      "ref": "BomRef.4163039673839164.8721598338563111"
    },
    {
      "ref": "BomRef.5143856245989535.31479272286686777"
    },
    {
      "ref": "BomRef.6151382959114065.603255116026117"
    },
    {
      "ref": "BomRef.1536463230913827.08985439939334261"
    },
    {
      "ref": "BomRef.6462312813033937.2621479055848642"
    },
    {
      "ref": "BomRef.24935674284071674.555881687061498"
    },
    {
      "ref": "BomRef.13342310505568067.8544589307764973"
    },
    {
      "ref": "BomRef.4332046246233626.795259628287604"
    },
    {
      "ref": "BomRef.7404108814614824.8235380783396934"
    },
    {
      "ref": "BomRef.9681147578453106.6688275495043436"
    },
    {
      "ref": "BomRef.5161906080021347.42942914405884414"
    },
    {
      "ref": "BomRef.34127043868134643.866309060882704"
    },
    {
      "ref": "BomRef.1386048560966291.26928365330098536"
    },
    {
      "ref": "BomRef.6626674822066282.5753537363610373"
    },
    {
      "ref": "BomRef.1221444837164426.8227553219357557"
    },
    {
      "ref": "BomRef.1465022172445608.9873832541034251"
    },
    {
      "ref": "BomRef.07075682868164312.7759608145017209"
    },
    {
      "ref": "BomRef.23127033617182946.5323053389621224"
    },
    {
      "ref": "BomRef.25732223634157314.5912645938585508"
    },
    {
      "ref": "BomRef.10322392442929362.7727491022392801"
    },
    {
      "ref": "BomRef.5182111008141962.38052236075242407"
    },
    {
      "ref": "BomRef.35008985117432023.19585014351176389"
    },
    {
      "ref": "BomRef.1770443783939466.5140651192506216"
    },
    {
      "ref": "BomRef.26622475399874324.2879557273623502"
    },
    {
      "ref": "BomRef.682710492317654.42864415874214024"
    },
    {
      "ref": "BomRef.08970936003800445.48019475208765916"
    },
    {
      "ref": "BomRef.3138472453565493.8555064766797252"
    },
    {
      "ref": "BomRef.5601384922185327.8133206776698153"
    },
    {
      "ref": "BomRef.3391512983596001.45219231548076877"
    },
    {
      "ref": "BomRef.5003552210738995.3907062292777187"
    },
    {
      "ref": "BomRef.600442768005774.6500937067157797"
    },
    {
      "ref": "BomRef.98036271256211.5157746391137943"
    },
    {
      "ref": "BomRef.6901366936913301.9919808150445804"
    },
    {
      "ref": "BomRef.3408896473274503.9368487815019755"
    },
    {
      "ref": "BomRef.963240332319471.9749109075176594"
    },
    {
      "ref": "BomRef.5262991904152454.9679632655820538"
    },
    {
      "ref": "BomRef.36377914192901684.7255922589274026"
    },
    {
      "ref": "BomRef.852237618535223.38176432624242973"
    },
    {
      "ref": "BomRef.3361937290990057.5415170028242486"
    },
    {
      "ref": "BomRef.9835140225109988.3152794327734316"
    },
    {
      "ref": "BomRef.43053608972442137.6032402051851337"
    },
    {
      "ref": "BomRef.06020692649238013.06418343785152214"
    },
    {
      "ref": "BomRef.7369724763288075.46114252730429817"
    },
    {
      "ref": "BomRef.7512641397111998.7551288420976054"
    },
    {
      "ref": "BomRef.4932871677499093.0224189405438473"
    },
    {
      "ref": "BomRef.39170836227087913.7703282097772005"
    },
    {
      "ref": "BomRef.8215994508676511.00854632602919303"
    },
    {
      "ref": "BomRef.9203214545372581.05810994057543206"
    },
    {
      "ref": "BomRef.7121768012460298.6831042096395753"
    },
    {
      "ref": "BomRef.1627680874005738.5186609440312644"
    },
    {
      "ref": "BomRef.16541512516813095.9052564952770752"
    },
    {
      "ref": "BomRef.9338470409129607.2521853204965865"
    },
    {
      "ref": "BomRef.6127446047378282.9359435920398181"
    },
    {
      "ref": "BomRef.13341543270359424.01229782532099899"
    },
    {
      "ref": "BomRef.011778688048470931.22352707167100394"
    },
    {
      "ref": "BomRef.4328767306113661.40246422189266073"
    },
    {
      "ref": "BomRef.5424360438525592.030663887187034278"
    },
    {
      "ref": "BomRef.14905616759135554.050103478276885216"
    },
    {
      "ref": "BomRef.1327657337657685.3242234189013058"
    },
    {
      "ref": "BomRef.12615683546768774.27374617166213633"
    },
    {
      "ref": "BomRef.014237553556579963.7480174564174986"
    },
    {
      "ref": "BomRef.4057145430137862.2571275299377813"
    },
    {
      "ref": "BomRef.3656307793308552.24327716599539562"
    },
    {
      "ref": "BomRef.8052639961416493.6147689178085999"
    },
    {
      "ref": "BomRef.8932264348629707.9145182314928945"
    },
    {
      "ref": "BomRef.6544864846486909.04028590421938172"
    },
    {
      "ref": "BomRef.35828333124285006.6001766890266548"
    },
    {
      "ref": "BomRef.34826734434729323.6776748954012676"
    },
    {
      "ref": "BomRef.9323151371034749.7106707591562522"
    },
    {
      "ref": "BomRef.24717121630101402.07694692293647698"
    },
    {
      "ref": "BomRef.9826696735306814.46239869143739676"
    },
    {
      "ref": "BomRef.4113561898744106.7392348054747258"
    },
    {
      "ref": "BomRef.1534385245076082.9825835538864264"
    },
    {
      "ref": "BomRef.1251784585184137.15926619193105784"
    },
    {
      "ref": "BomRef.8981077033738266.39562307316455336"
    },
    {
      "ref": "BomRef.8499271343700612.8696909254878976"
    },
    {
      "ref": "BomRef.7976660706590307.030706747349566466"
    },
    {
      "ref": "BomRef.7496955586628976.9258868812329143"
    },
    {
      "ref": "BomRef.19797194730623924.5016579949849717"
    },
    {
      "ref": "BomRef.6120550821978259.25270254343500387"
    },
    {
      "ref": "BomRef.7217190445856247.6026094728385979"
    },
    {
      "ref": "BomRef.1327220946308606.2861368968213518"
    },
    {
      "ref": "BomRef.6605638518627277.01090445794710082"
    },
    {
      "ref": "BomRef.9229369251969962.3566474889180804"
    },
    {
      "ref": "BomRef.33873635126331325.04658383771796082"
    },
    {
      "ref": "BomRef.7060923243670211.14971721147863426"
    },
    {
      "ref": "BomRef.28629903892246567.07367799981057188"
    },
    {
      "ref": "BomRef.27036339601431003.7051994140302649"
    },
    {
      "ref": "BomRef.740487180202749.7161350696325692"
    },
    {
      "ref": "BomRef.5705031417022018.14384537981158685"
    },
    {
      "ref": "BomRef.4343177735279167.0818065469150101"
    },
    {
      "ref": "BomRef.6765455978351402.8395952836629234"
    },
    {
      "ref": "BomRef.12653998161655167.6696903719481841"
    },
    {
      "ref": "BomRef.2718892667322874.009678597920913967"
    },
    {
      "ref": "BomRef.23094932474050278.5740898052130355"
    },
    {
      "ref": "BomRef.24297854408542374.19366761939615362"
    },
    {
      "ref": "BomRef.04657273264806916.677565532276889"
    },
    {
      "ref": "BomRef.1433240813212171.6392183393420439"
    },
    {
      "ref": "BomRef.7108283339811768.9438567408422134"
    },
    {
      "ref": "BomRef.8470423003993348.01881575672729252"
    },
    {
      "ref": "BomRef.16851407482773595.7080761122825618"
    },
    {
      "ref": "BomRef.5339868961406974.43470824808629094"
    },
    {
      "ref": "BomRef.7656164204429826.21401876124320707"
    },
    {
      "ref": "BomRef.20152316681322413.11971995223583687"
    },
    {
      "ref": "BomRef.5653994102778257.17328362019203847"
    },
    {
      "ref": "BomRef.2718569389293576.31509873141412714"
    },
    {
      "ref": "BomRef.32322304689592296.4371370821480344"
    },
    {
      "ref": "BomRef.041474408515578154.29461221901426937"
    },
    {
      "ref": "BomRef.9826538464816856.4249924816879952"
    },
    {
      "ref": "BomRef.20197738668356569.12362760966499176"
    },
    {
      "ref": "BomRef.1849337867826515.006010181925209412"
    },
    {
      "ref": "BomRef.846494587719508.4409436280768897"
    },
    {
      "ref": "BomRef.5516933293426147.38897780280154215"
    },
    {
      "ref": "BomRef.8987280021314258.09277677697065778"
    },
    {
      "ref": "BomRef.5583134261799152.005789343868171426"
    },
    {
      "ref": "BomRef.5720773909119735.655829179847459"
    },
    {
      "ref": "BomRef.5857884642730372.2447656007169322"
    },
    {
      "ref": "BomRef.44216418902636623.06171839754069686"
    },
    {
      "ref": "BomRef.276387535283111.5133178308141938"
    },
    {
      "ref": "BomRef.2836253736820884.9212049784442881"
    },
    {
      "ref": "BomRef.20374067573944732.18922272075370095"
    },
    {
      "ref": "BomRef.39571201244158605.882806601930204"
    },
    {
      "ref": "BomRef.33593225769714563.662417880734105"
    },
    {
      "ref": "BomRef.02920202793639226.4061500698107986"
    },
    {
      "ref": "BomRef.4111481239815634.008889975959184393"
    },
    {
      "ref": "BomRef.06689032713488607.4758234521990906"
    },
    {
      "ref": "BomRef.9502825961959741.014272907473487861"
    },
    {
      "ref": "BomRef.21011629014372335.4089891184483605"
    },
    {
      "ref": "BomRef.913881848939455.7432187220956539"
    },
    {
      "ref": "BomRef.6843253347331526.09920479879743993"
    },
    {
      "ref": "BomRef.023600669464129753.12663440323180186"
    },
    {
      "ref": "BomRef.10222450190787624.8393892854067819"
    },
    {
      "ref": "BomRef.9124854810325875.9992646704209204"
    },
    {
      "ref": "BomRef.6170930576622515.48956887652803716"
    },
    {
      "ref": "BomRef.6911098846894638.31143684791512527"
    },
    {
      "ref": "BomRef.22219313044209776.18808922021972918"
    },
    {
      "ref": "BomRef.17167385280203662.5311187481123368"
    },
    {
      "ref": "BomRef.025295149269627504.8414669465129304"
    },
    {
      "ref": "BomRef.858155205960467.21581761615022133"
    },
    {
      "ref": "BomRef.44511421971960474.2372168641203516"
    },
    {
      "ref": "BomRef.47149787444060154.8902691181260931"
    },
    {
      "ref": "BomRef.251537048304346.5005325666393251"
    },
    {
      "ref": "BomRef.5852695049603781.9134287684946485"
    },
    {
      "ref": "BomRef.4332150928287344.7065713403098943"
    },
    {
      "ref": "BomRef.8539035724795038.41542171097367386"
    },
    {
      "ref": "BomRef.8976575313785282.2914042026667628"
    },
    {
      "ref": "BomRef.6905230875766468.24682986596963696"
    },
    {
      "ref": "BomRef.16173929747576932.8872161670530829"
    },
    {
      "ref": "BomRef.03339074331216885.3188713807186522"
    },
    {
      "ref": "BomRef.3207145307095982.6978047928762252"
    },
    {
      "ref": "BomRef.7024103039190571.6097066509142984"
    },
    {
      "ref": "BomRef.5251403681174225.07841039477913292"
    },
    {
      "ref": "BomRef.0035630277068516847.34788069831357815"
    },
    {
      "ref": "BomRef.5334431523884916.7990645009699633"
    },
    {
      "ref": "BomRef.5432439236730557.1073254811412715"
    },
    {
      "ref": "BomRef.6029353764700056.588245875339538"
    },
    {
      "ref": "BomRef.23141321568324302.23173845792832248"
    },
    {
      "ref": "BomRef.35335305338327405.3759625309452961"
    },
    {
      "ref": "BomRef.8161794048283197.3362457299824254"
    },
    {
      "ref": "BomRef.2184711287908827.1419380358948541"
    },
    {
      "ref": "BomRef.3481024200346844.9869917203056577"
    },
    {
      "ref": "BomRef.25684005608963445.051982655765296704"
    },
    {
      "ref": "BomRef.6346216305408744.6144272239685917"
    },
    {
      "ref": "BomRef.737936946998565.18598325302298013"
    },
    {
      "ref": "BomRef.31010031991354936.8893650556821875"
    },
    {
      "ref": "BomRef.9414083722861952.7553647359376754"
    },
    {
      "ref": "BomRef.3296973027258866.5097190006324973"
    },
    {
      "ref": "BomRef.20835658578268057.7545467164833245"
    },
    {
      "ref": "BomRef.7899100850130666.40491384981354894"
    },
    {
      "ref": "BomRef.4057132859789465.9201080560125651"
    },
    {
      "ref": "BomRef.25846218655874553.023540006096414712"
    },
    {
      "ref": "BomRef.22322305500655615.7259018798645404"
    },
    {
      "ref": "BomRef.9565753312499307.9762125310998879"
    },
    {
      "ref": "BomRef.039609365541825925.4650890568347327"
    },
    {
      "ref": "BomRef.11808006121211145.9136288674349349"
    },
    {
      "ref": "BomRef.2873633954717466.5535403179959095"
    },
    {
      "ref": "BomRef.4596064525678152.346646905019781"
    },
    {
      "ref": "BomRef.7908515018216623.21528889751206648"
    },
    {
      "ref": "BomRef.07268367392223707.3982109485165506"
    },
    {
      "ref": "BomRef.3477145517965913.8899302806195817"
    },
    {
      "ref": "BomRef.3925809375842787.8008994554688549"
    },
    {
      "ref": "BomRef.09530598133011892.26477424285906914"
    },
    {
      "ref": "BomRef.6813533464145896.7599568182049437"
    },
    {
      "ref": "BomRef.9497066492793391.30328190280453016"
    },
    {
      "ref": "BomRef.8218577507745715.8953983124629376"
    },
    {
      "ref": "BomRef.4753725220583813.3827155181118329"
    },
    {
      "ref": "BomRef.1345852956217738.8939240068957326"
    },
    {
      "ref": "BomRef.4229789637855441.1460474663629001"
    },
    {
      "ref": "BomRef.8999332631300351.5822771674740229"
    },
    {
      "ref": "BomRef.6176153901015593.26000802744580176"
    },
    {
      "ref": "BomRef.7370740613860806.21362891363552272"
    },
    {
      "ref": "BomRef.7975154259919881.36301840856229795"
    },
    {
      "ref": "BomRef.7653190340656153.6991233921976238"
    },
    {
      "ref": "BomRef.3773776805572848.23351173862201702"
    },
    {
      "ref": "BomRef.1306250432733057.9833875354353265"
    },
    {
      "ref": "BomRef.900909762249451.2471445380985453"
    },
    {
      "ref": "BomRef.22543845512421035.07580705229318907"
    },
    {
      "ref": "BomRef.4780380484421286.4501137849361958"
    },
    {
      "ref": "BomRef.09543390922248007.37725492866851484"
    },
    {
      "ref": "BomRef.18174864459036222.8392115375244704"
    },
    {
      "ref": "BomRef.104184760759366.9641630516882661"
    },
    {
      "ref": "BomRef.1928098138627412.22162106785403124"
    },
    {
      "ref": "BomRef.3873623856203078.988632204137638"
    },
    {
      "ref": "BomRef.013815427444148431.9711292275871117"
    },
    {
      "ref": "BomRef.11075272586353913.5411272225418162"
    },
    {
      "ref": "BomRef.12687764016661762.27258319889775984"
    },
    {
      "ref": "BomRef.0018159720216502917.7278583532015503"
    },
    {
      "ref": "BomRef.40425564798806934.35936938820893904"
    },
    {
      "ref": "BomRef.23580104330413765.611528235415045"
    },
    {
      "ref": "BomRef.3459249345148202.7826137119515066"
    },
    {
      "ref": "BomRef.5385626187911724.6197900783544131"
    },
    {
      "ref": "BomRef.6647904219132164.9431811920417164"
    },
    {
      "ref": "BomRef.4464815583687167.5676416688092596"
    },
    {
      "ref": "BomRef.5834045117863439.6701370175415429"
    },
    {
      "ref": "BomRef.09613787870217028.028285942197263325"
    },
    {
      "ref": "BomRef.9136498816516799.4942325872386133"
    },
    {
      "ref": "BomRef.48510772204240515.01610398379080613"
    },
    {
      "ref": "BomRef.45000904472512826.11234631717478016"
    },
    {
      "ref": "BomRef.02979587136401929.1070087129761298"
    },
    {
      "ref": "BomRef.17485222034003423.3263128649505064"
    },
    {
      "ref": "BomRef.44766284115186505.5433824599208427"
    },
    {
      "ref": "BomRef.9626647589522044.7048965793322094"
    },
    {
      "ref": "BomRef.9765370120590116.10861593621240972"
    },
    {
      "ref": "BomRef.15304201089770242.36036912060642323"
    },
    {
      "ref": "BomRef.25791499920134964.39677555165238476"
    },
    {
      "ref": "BomRef.7912872795152134.48040140019081556"
    },
    {
      "ref": "BomRef.9431395505965606.7215658594590812"
    },
    {
      "ref": "BomRef.16792030304685956.554699020554485"
    },
    {
      "ref": "BomRef.5916494689057641.7447443405295717"
    },
    {
      "ref": "BomRef.14817197870407994.5075396378238253"
    },
    {
      "ref": "BomRef.8862275764384353.9316362234120903"
    },
    {
      "ref": "BomRef.4903335268428829.005686469324557741"
    },
    {
      "ref": "BomRef.8073897311222961.32583908020053953"
    },
    {
      "ref": "BomRef.8625073871317434.9251194753306632"
    },
    {
      "ref": "BomRef.7306780567283283.910009484611246"
    },
    {
      "ref": "BomRef.006912398675142262.6368006183016659"
    },
    {
      "ref": "BomRef.4533280492974202.824416915091"
    },
    {
      "ref": "BomRef.4341661832905582.16991957960361714"
    },
    {
      "ref": "BomRef.7456804602700163.26626888603001986"
    },
    {
      "ref": "BomRef.7332335535825006.9635273963684483"
    },
    {
      "ref": "BomRef.8341756848387535.13477933004979548"
    },
    {
      "ref": "BomRef.8238929013812966.030589068594395363"
    },
    {
      "ref": "BomRef.5584092863906518.45555823535751716"
    },
    {
      "ref": "BomRef.16793730416219266.2801808716669726"
    },
    {
      "ref": "BomRef.057313276622598774.9776153662302206"
    },
    {
      "ref": "BomRef.7432538448193754.22737816154470392"
    },
    {
      "ref": "BomRef.9172951059655089.18235788502309047"
    },
    {
      "ref": "BomRef.9293946820657696.028474406284301645"
    },
    {
      "ref": "BomRef.8878718790485854.4329488554368076"
    },
    {
      "ref": "BomRef.06259665202502329.3451017927482022"
    },
    {
      "ref": "BomRef.8076593480616812.025504375254326028"
    },
    {
      "ref": "BomRef.46763223007709875.39533186752785854"
    },
    {
      "ref": "BomRef.9392930118593713.03377714464804471"
    },
    {
      "ref": "BomRef.7083726510006625.7408208402061585"
    },
    {
      "ref": "BomRef.5619578338351288.07469094128218068"
    },
    {
      "ref": "BomRef.9675185747023164.16839193040169587"
    },
    {
      "ref": "BomRef.8903178854084978.8122913040999395"
    },
    {
      "ref": "BomRef.8584033439899356.8087748123904388"
    },
    {
      "ref": "BomRef.3379224207803291.15941274452484044"
    },
    {
      "ref": "BomRef.8273649672068532.22268476662144843"
    },
    {
      "ref": "BomRef.770330096082.14196121435599818"
    },
    {
      "ref": "BomRef.2602288839805458.33356986267987576"
    },
    {
      "ref": "BomRef.4078619752080975.44863080079965756"
    },
    {
      "ref": "BomRef.08475292186363903.6018528409900756"
    },
    {
      "ref": "BomRef.7566639174475305.22562845280221755"
    },
    {
      "ref": "BomRef.37861571185710496.2828002707878283"
    },
    {
      "ref": "BomRef.45524013444249667.7216126593765714"
    },
    {
      "ref": "BomRef.32714504131001143.2992682437445213"
    },
    {
      "ref": "BomRef.46986298307002683.7418385068126757"
    },
    {
      "ref": "BomRef.8556480701790246.3191276740764548"
    },
    {
      "ref": "BomRef.8770835651682857.8446927283409736"
    },
    {
      "ref": "BomRef.4862980005505837.9071629537158274"
    },
    {
      "ref": "BomRef.6686601367683058.39502771817966664"
    },
    {
      "ref": "BomRef.6284838634327398.3003337996424428"
    },
    {
      "ref": "BomRef.7322872065675041.9842000577204513"
    },
    {
      "ref": "BomRef.004215663645203538.30930630725570707"
    },
    {
      "ref": "BomRef.6007384753361936.39896805651472056"
    },
    {
      "ref": "BomRef.30936223483257197.3256611094106132"
    },
    {
      "ref": "BomRef.670175967420862.6132685907118344"
    },
    {
      "ref": "BomRef.8842375263146283.7306104662909028"
    },
    {
      "ref": "BomRef.7594428262248059.11074467512512376"
    },
    {
      "ref": "BomRef.9746750087204098.4251624987262007"
    },
    {
      "ref": "BomRef.8575760421906526.7889713879361278"
    },
    {
      "ref": "BomRef.7828524875599515.6108137700826161"
    },
    {
      "ref": "BomRef.026725048478927205.9381030242226183"
    },
    {
      "ref": "BomRef.36678025112905366.44799180451080767"
    },
    {
      "ref": "BomRef.9066164707350783.2581649911592804"
    },
    {
      "ref": "pkg:oci/tomcat@9.0.70-jdk8-corretto?digest=sha256:93d42e4f4a441739bea9361d59917263d65d4d9b3c0e946b4ccd3ce939812f9c",
      "dependsOn": [
        "BomRef.9502825961959741.014272907473487861",
        "BomRef.1465022172445608.9873832541034251",
        "BomRef.13341543270359424.01229782532099899",
        "BomRef.7639158257292504.21522534253298442",
        "BomRef.9826538464816856.4249924816879952",
        "BomRef.19797194730623924.5016579949849717",
        "BomRef.21011629014372335.4089891184483605",
        "BomRef.8470423003993348.01881575672729252",
        "BomRef.33593225769714563.662417880734105",
        "BomRef.14639827735184152.8100529945700642",
        "BomRef.33873635126331325.04658383771796082",
        "BomRef.4343177735279167.0818065469150101",
        "BomRef.1221444837164426.8227553219357557",
        "BomRef.7108283339811768.9438567408422134",
        "BomRef.7958113284835122.8956586277046765",
        "BomRef.7060923243670211.14971721147863426",
        "BomRef.20152316681322413.11971995223583687",
        "BomRef.6170930576622515.48956887652803716",
        "BomRef.7512641397111998.7551288420976054",
        "BomRef.3243847038058433.6434280073928325",
        "BomRef.5601384922185327.8133206776698153",
        "BomRef.7404108814614824.8235380783396934",
        "BomRef.39170836227087913.7703282097772005",
        "BomRef.5516933293426147.38897780280154215",
        "BomRef.1536463230913827.08985439939334261",
        "BomRef.16541512516813095.9052564952770752",
        "BomRef.34826734434729323.6776748954012676",
        "BomRef.25732223634157314.5912645938585508",
        "BomRef.6120550821978259.25270254343500387",
        "BomRef.7656164204429826.21401876124320707",
        "BomRef.20374067573944732.18922272075370095",
        "BomRef.6462312813033937.2621479055848642",
        "BomRef.2718569389293576.31509873141412714",
        "BomRef.10870588622353639.5792501550856259",
        "BomRef.4332046246233626.795259628287604",
        "BomRef.2718892667322874.009678597920913967",
        "BomRef.1849337867826515.006010181925209412",
        "BomRef.5990787889226832.3917259225513092",
        "BomRef.041474408515578154.29461221901426937",
        "BomRef.8649550122428052.08255056361006696",
        "BomRef.10222450190787624.8393892854067819",
        "BomRef.3971915537463303.551799956122311",
        "BomRef.4163039673839164.8721598338563111",
        "BomRef.9119207184919825.2852014807529095",
        "BomRef.27036339601431003.7051994140302649",
        "BomRef.9338470409129607.2521853204965865",
        "BomRef.4057145430137862.2571275299377813",
        "BomRef.3904649021228791.6391495186657729",
        "BomRef.5720773909119735.655829179847459",
        "BomRef.1251784585184137.15926619193105784",
        "BomRef.7952778068009224.04545893801380796",
        "BomRef.5182111008141962.38052236075242407",
        "BomRef.6626674822066282.5753537363610373",
        "BomRef.3138472453565493.8555064766797252",
        "BomRef.3656307793308552.24327716599539562",
        "BomRef.8323112021785808.19369969194680703",
        "BomRef.5857884642730372.2447656007169322",
        "BomRef.6605638518627277.01090445794710082",
        "BomRef.9168960829352993.9985037916173709",
        "BomRef.36377914192901684.7255922589274026",
        "BomRef.963240332319471.9749109075176594",
        "BomRef.276387535283111.5133178308141938",
        "BomRef.4932871677499093.0224189405438473",
        "BomRef.6901366936913301.9919808150445804",
        "BomRef.2836253736820884.9212049784442881",
        "BomRef.7217190445856247.6026094728385979",
        "BomRef.6843253347331526.09920479879743993",
        "BomRef.3391512983596001.45219231548076877",
        "BomRef.8499271343700612.8696909254878976",
        "BomRef.852237618535223.38176432624242973",
        "BomRef.682710492317654.42864415874214024",
        "BomRef.8215994508676511.00854632602919303",
        "BomRef.1327220946308606.2861368968213518",
        "BomRef.06689032713488607.4758234521990906",
        "BomRef.4878951036338821.14080929949471943",
        "BomRef.07075682868164312.7759608145017209",
        "BomRef.9203214545372581.05810994057543206",
        "BomRef.011778688048470931.22352707167100394",
        "BomRef.98036271256211.5157746391137943",
        "BomRef.35828333124285006.6001766890266548",
        "BomRef.23094932474050278.5740898052130355",
        "BomRef.16851407482773595.7080761122825618",
        "BomRef.9681147578453106.6688275495043436",
        "BomRef.5143856245989535.31479272286686777",
        "BomRef.1327657337657685.3242234189013058",
        "BomRef.740487180202749.7161350696325692",
        "BomRef.14905616759135554.050103478276885216",
        "BomRef.913881848939455.7432187220956539",
        "BomRef.20197738668356569.12362760966499176",
        "BomRef.02920202793639226.4061500698107986",
        "BomRef.5003552210738995.3907062292777187",
        "BomRef.7496955586628976.9258868812329143",
        "BomRef.3327266175021557.5372064892065355",
        "BomRef.3361937290990057.5415170028242486",
        "BomRef.06020692649238013.06418343785152214",
        "BomRef.5339868961406974.43470824808629094",
        "BomRef.24717121630101402.07694692293647698",
        "BomRef.4113561898744106.7392348054747258",
        "BomRef.6151382959114065.603255116026117",
        "BomRef.23127033617182946.5323053389621224",
        "BomRef.6772436204217235.5812130418147848",
        "BomRef.9826696735306814.46239869143739676",
        "BomRef.5653994102778257.17328362019203847",
        "BomRef.8981077033738266.39562307316455336",
        "BomRef.8052639961416493.6147689178085999",
        "BomRef.1627680874005738.5186609440312644",
        "BomRef.8932264348629707.9145182314928945",
        "BomRef.04657273264806916.677565532276889",
        "BomRef.5583134261799152.005789343868171426",
        "BomRef.1534385245076082.9825835538864264",
        "BomRef.34127043868134643.866309060882704",
        "BomRef.35008985117432023.19585014351176389",
        "BomRef.4328767306113661.40246422189266073",
        "BomRef.1386048560966291.26928365330098536",
        "BomRef.6544864846486909.04028590421938172",
        "BomRef.5705031417022018.14384537981158685",
        "BomRef.1433240813212171.6392183393420439",
        "BomRef.023600669464129753.12663440323180186",
        "BomRef.9323151371034749.7106707591562522",
        "BomRef.5262991904152454.9679632655820538",
        "BomRef.26622475399874324.2879557273623502",
        "BomRef.12653998161655167.6696903719481841",
        "BomRef.9835140225109988.3152794327734316",
        "BomRef.1770443783939466.5140651192506216",
        "BomRef.9124854810325875.9992646704209204",
        "BomRef.12615683546768774.27374617166213633",
        "BomRef.28629903892246567.07367799981057188",
        "BomRef.24935674284071674.555881687061498",
        "BomRef.846494587719508.4409436280768897",
        "BomRef.6911098846894638.31143684791512527",
        "BomRef.6863074463388752.04903501527493381",
        "BomRef.23373836527391423.728442297836659",
        "BomRef.44216418902636623.06171839754069686",
        "BomRef.8987280021314258.09277677697065778",
        "BomRef.13342310505568067.8544589307764973",
        "BomRef.08970936003800445.48019475208765916",
        "BomRef.6127446047378282.9359435920398181",
        "BomRef.7976660706590307.030706747349566466",
        "BomRef.32322304689592296.4371370821480344",
        "BomRef.5161906080021347.42942914405884414",
        "BomRef.4111481239815634.008889975959184393",
        "BomRef.6765455978351402.8395952836629234",
        "BomRef.014237553556579963.7480174564174986",
        "BomRef.7121768012460298.6831042096395753",
        "BomRef.3408896473274503.9368487815019755",
        "BomRef.9229369251969962.3566474889180804",
        "BomRef.39571201244158605.882806601930204",
        "BomRef.5424360438525592.030663887187034278",
        "BomRef.10322392442929362.7727491022392801",
        "BomRef.43053608972442137.6032402051851337",
        "BomRef.7369724763288075.46114252730429817",
        "BomRef.600442768005774.6500937067157797",
        "BomRef.24297854408542374.19366761939615362"
      ]
    }
  ],
  "serialNumber": "urn:uuid:62a5ecf5-c7eb-4e31-b075-f40d992a710f"
}